australians_calendar/__init__.py
australians_calendar/constants.py
australians_calendar/solar_terms.py
australians_calendar/utils.py
australianscalendar-1.0.0.dist-info/LICENSE
australianscalendar-1.0.0.dist-info/METADATA
australianscalendar-1.0.0.dist-info/WHEEL
australianscalendar-1.0.0.dist-info/top_level.txt
australianscalendar-1.0.0.dist-info/RECORD
