Metadata-Version: 2.1
Name: australianscalendar
Version: 1.0.0
Summary: check if some day is holiday in Australia
Home-page: https://github.com/hack-fang/australian-calendar
Author: Hack Fang
Author-email: kaifang.1995@gmail.com
License: MIT License
Classifier: License :: OSI Approved :: MIT License
Classifier: Programming Language :: Python :: 3
Classifier: Programming Language :: Python :: 3.8
Classifier: Programming Language :: Python :: 3.9
Classifier: Programming Language :: Python :: 3.10
Classifier: Programming Language :: Python :: 3.11
Classifier: Programming Language :: Python :: 3.12
License-File: LICENSE
